Workbook
Name NativeTimeline_Start_Date: #N/A
Name Slicer_Department: #N/A
Name Slicer_Department: #N/A
Name Slicer_Department1: #N/A
Name Slicer_Experience: #N/A
Name Slicer_Experience: #N/A
Name Slicer_Region: #N/A
Name Slicer_Region: #N/A
Name Slicer_status: #N/A
Name Slicer_status: #N/A

Sheet Dashboard
A1: EMPLOYEEE AND HR DASHBOARD
A4: TOTAL EMPLOYEES | D4: AVERAGE SALARY | G4: AVERAGE EXPERIENCE | J4: ACTIVE EMPLOYEES | M4: TOTAL BONUS
A5: =COUNTA('[1]Data cleaning and validation(3)'!A2:A1001) -> 1000 | D5: =AVERAGE('[1]Data cleaning and validation(3)'!J2:J1001) -> 97331.223 | G5: =AVERAGE('[1]Data cleaning and validation(3)'!I2:I1001) -> 13.888 | J5: =COUNTIF('[1]Data cleaning and validation(3)'!O1:O1001,"Active") -> #VALUE! | M5: =SUM('[1]Data cleaning and validation(3)'!Q2:Q1001) -> 0
O10: KEY INSIGHTS
O11: • Clothing has the highest employee count with 53 employees.
O12: • Outdoors has the highest average salary at ₹112,055.
O13: • 853 employees are Active, representing 85.2% of the dataset.
O14: • Southwest has the highest employee count among regions with 168 employees.
O15: • USA accounts for the largest share of employees with 594 employees.
O16: • The highest individual salary is ₹149,929, held by a Director of Sales.

Sheet RawData(1)
A1: ID | B1: Last Name | C1: email | D1: Gender | E1: Department | F1: Start Date | G1: Start date | H1: Current | I1: Experience | J1: Salary | K1: Job title | L1: Region | M1: Region | N1: Country | O1: Divisons
A2: 1 | B2: Kelley | C2: rkelley0@soundcloud.com | D2: Female | E2: Computers | F2: 40088 | G2: 2009 | H2: 2021 | I2: 12 | J2: 67470 | K2: Structural Engineer | L2: 2 | M2: Southeast | N2: USA | O2: Electronic Equipment
A3: 2 | B3: Armstrong | C3: sarmstrong1@infoseek.co.jp | D3: Male | E3: Sports | F3: 39538 | G3: 2008 | H3: 2021 | I3: 13 | J3: 71869 | K3: Financial Advisor | L3: 2 | M3: Southeast | N3: USA | O3: Games & Sports
A4: 3 | B4: Carr | C4: fcarr2@woothemes.com | D4: Male | E4: Automotive | F4: 40006 | G4: 2009 | H4: 2021 | I4: 12 | J4: 101768 | K4: Recruiting Manager | L4: 3 | M4: Northwest | N4: USA | O4: Auto & Hardware
A5: 4 | B5: Murray | C5: jmurray3@gov.uk | D5: Female | E5: Jewelery | F5: 41998 | G5: 2014 | H5: 2021 | I5: 7 | J5: 96897 | K5: Desktop Support Technician | L5: 3 | M5: Northwest | N5: USA | O5: Fashion
A6: 5 | B6: Ellis | C6: jellis4@sciencedirect.com | D6: Female | E6: Grocery | F6: 37518 | G6: 2002 | H6: 2021 | I6: 19 | J6: 63702 | K6: Software Engineer III | L6: 7 | M6: Nova Scotia | N6: Canada | O6: Domestic
A7: 6 | B7: Phillips | C7: bphillips5@time.com | D7: Male | E7: Tools | F7: 41507 | G7: 2013 | H7: 2021 | I7: 8 | J7: 118497 | K7: Executive Secretary | L7: 1 | M7: Northeast | N7: USA | O7: Auto & Hardware
A8: 7 | B8: Williamson | C8: rwilliamson6@ted.com | D8: Male | E8: Computers | F8: 38851 | G8: 2006 | H8: 2021 | I8: 15 | J8: 65889 | K8: Dental Hygienist | L8: 6 | M8: Quebec | N8: Canada | O8: Electronic Equipment
A9: 8 | B9: Harris | C9: aharris7@ucoz.com | D9: Female | E9: Toys | F9: 37845 | G9: 2003 | H9: 2021 | I9: 18 | J9: 84427 | K9: Safety Technician I | L9: 4 | M9: Southwest | N9: USA | O9: Games & Sports
A10: 9 | B10: James | C10: rjames8@prnewswire.com | D10: Male | E10: Jewelery | F10: 38602 | G10: 2005 | H10: 2021 | I10: 16 | J10: 108657 | K10: Sales Associate | L10: 2 | M10: Southeast | N10: USA | O10: Fashion
A11: 10 | B11: Sanchez | C11: rsanchez9@cloudflare.com | D11: Male | E11: Movies | F11: 41346 | G11: 2013 | H11: 2021 | I11: 8 | J11: 108093 | K11: Sales Representative | L11: 1 | M11: Northeast | N11: USA | O11: Entertainment
A12: 11 | B12: Jacobs | C12: jjacobsa@sbwire.com | D12: Female | E12: Jewelery | F12: 37952 | G12: 2003 | H12: 2021 | I12: 18 | J12: 121966 | K12: Community Outreach Specialist | L12: 7 | M12: Nova Scotia | N12: Canada | O12: Fashion
A13: 12 | B13: Black | C13: mblackb@edublogs.org | D13: Male | E13: Clothing | F13: 37656 | G13: 2003 | H13: 2021 | I13: 18 | J13: 44179 | K13: Data Coordiator | L13: 7 | M13: Nova Scotia | N13: Canada | O13: Domestic
... A1001: 1000 | B1001: Howard | C1001: showardrr@addtoany.com | D1001: Male | E1001: Baby | F1001: 37932 | G1001: 2003 | H1001: 2021 | I1001: 18 | J1001: 148687 | K1001: General Manager | L1001: 3 | M1001: Northwest | N1001: USA | O1001: Domestic

Sheet Formatted Data(2)
K3: Comparing salaries and highlighting them if they are greater than the valure that need to be checked | M3: 100000
A6: ID | B6: Last Name | C6: email | D6: Sex | E6: Department | F6: Start Date | G6: Start date2 | H6: Current | I6: Experience | J6: Salary | K6: Job title | L6: Region | M6: Region2 | N6: Country | O6: Divisions | P6: status | Q6: Annual Salary | R6: BONUS
A7: 1 | B7: Kelley | C7: rkelley0@soundcloud.com | D7: F | E7: Computers | F7: 44836 | G7: 2009 | H7: 2021 | I7: 12 | J7: 67470 | K7: Structural Engineer | L7: 2 | M7: Southeast | N7: USA | O7: Electronic Equipment | P7: Active | Q7: =J7*12 -> 809640 | R7: =J7*10% -> 6747
A8: 2 | B8: Armstrong | C8: sarmstrong1@infoseek.co.jp | D8: M | E8: Sports | F8: 39538 | G8: 2008 | H8: 2021 | I8: 13 | J8: 71869 | K8: Financial Advisor | L8: 2 | M8: Southeast | N8: USA | O8: Games & Sports | P8: On Leave | Q8: =J8*12 -> 862428 | R8: =J8*10% -> 7186.9
A9: 3 | B9: Carr | C9: fcarr2@woothemes.com | D9: M | E9: Automotive | F9: 40006 | G9: 2009 | H9: 2021 | I9: 12 | J9: 101768 | K9: Recruiting Manager | L9: 3 | M9: Northwest | N9: USA | O9: Auto & Hardware | P9: Resigned | Q9: =J9*12 -> 1221216 | R9: =J9*10% -> 10176.8
A10: 4 | B10: Murray | C10: jmurray3@gov.uk | D10: F | E10: Jewelery | F10: 46746 | G10: 2014 | H10: 2021 | I10: 7 | J10: 96897 | K10: Desktop Support Technician | L10: 3 | M10: Northwest | N10: USA | O10: Fashion | P10: On Leave | Q10: =J10*12 -> 1162764 | R10: =J10*10% -> 9689.7
A11: 5 | B11: Ellis | C11: jellis4@sciencedirect.com | D11: F | E11: Grocery | F11: 37518 | G11: 2002 | H11: 2021 | I11: 19 | J11: 63702 | K11: Software Engineer III | L11: 7 | M11: Nova Scotia | N11: Canada | O11: Domestic | P11: Active | Q11: =J11*12 -> 764424 | R11: =J11*10% -> 6370.2
A12: 6 | B12: Phillips | C12: bphillips5@time.com | D12: M | E12: Tools | F12: 41507 | G12: 2013 | H12: 2021 | I12: 8 | J12: 118497 | K12: Executive Secretary | L12: 1 | M12: Northeast | N12: USA | O12: Auto & Hardware | P12: Active | Q12: =J12*12 -> 1421964 | R12: =J12*10% -> 11849.7
A13: 7 | B13: Williamson | C13: rwilliamson6@ted.com | D13: M | E13: Computers | F13: 38851 | G13: 2006 | H13: 2021 | I13: 15 | J13: 65889 | K13: Dental Hygienist | L13: 6 | M13: Quebec | N13: Canada | O13: Electronic Equipment | P13: Active | Q13: =J13*12 -> 790668 | R13: =J13*10% -> 6588.9
A14: 8 | B14: Harris | C14: aharris7@ucoz.com | D14: F | E14: Toys | F14: 37845 | G14: 2003 | H14: 2021 | I14: 18 | J14: 84427 | K14: Safety Technician I | L14: 4 | M14: Southwest | N14: USA | O14: Games & Sports | P14: Active | Q14: =J14*12 -> 1013124 | R14: =J14*10% -> 8442.7
A15: 9 | B15: James | C15: rjames8@prnewswire.com | D15: M | E15: Jewelery | F15: 38602 | G15: 2005 | H15: 2021 | I15: 16 | J15: 108657 | K15: Sales Associate | L15: 2 | M15: Southeast | N15: USA | O15: Fashion | P15: Active | Q15: =J15*12 -> 1303884 | R15: =J15*10% -> 10865.7
A16: 10 | B16: Sanchez | C16: rsanchez9@cloudflare.com | D16: M | E16: Movies | F16: 41346 | G16: 2013 | H16: 2021 | I16: 8 | J16: 108093 | K16: Sales Representative | L16: 1 | M16: Northeast | N16: USA | O16: Entertainment | P16: Active | Q16: =J16*12 -> 1297116 | R16: =J16*10% -> 10809.3
A17: 11 | B17: Jacobs | C17: jjacobsa@sbwire.com | D17: F | E17: Jewelery | F17: 37952 | G17: 2003 | H17: 2021 | I17: 18 | J17: 121966 | K17: Community Outreach Specialist | L17: 7 | M17: Nova Scotia | N17: Canada | O17: Fashion | P17: Active | Q17: =J17*12 -> 1463592 | R17: =J17*10% -> 12196.6
A18: 12 | B18: Black | C18: mblackb@edublogs.org | D18: M | E18: Clothing | F18: 37656 | G18: 2003 | H18: 2021 | I18: 18 | J18: 44179 | K18: Data Coordinator | L18: 7 | M18: Nova Scotia | N18: Canada | O18: Domestic | P18: Active | Q18: =J18*12 -> 530148 | R18: =J18*10% -> 4417.9
... A1006: 1000 | B1006: Howard | C1006: showardrr@addtoany.com | D1006: M | E1006: Baby | F1006: 37932 | G1006: 2003 | H1006: 2021 | I1006: 18 | J1006: 148687 | K1006: General Manager | L1006: 3 | M1006: Northwest | N1006: USA | O1006: Domestic | P1006: Active | Q1006: =J1006*12 -> 1784244 | R1006: =J1006*10% -> 14868.7
A1007: Total | D1007: =SUBTOTAL(103,EMP_TABLE[Sex]) -> 1000 | O1007: =SUBTOTAL(103,EMP_TABLE[Divisions]) -> 1000

Sheet Data cleaning and validation(3)
A1: ID | B1: Last Name | C1: email | D1: Sex | E1: Department | F1: Start Date | G1: Experience | H1: Salary | I1: Job title | J1: Region | K1: Country | L1: Divisons | M1: status | N1: Annual Salary | O1: BONUS
A2: 1 | B2: Kelley | C2: rkelley0@soundcloud.com | D2: F | E2: Computers | F2: 44836 | G2: 12 | H2: 67470 | I2: Structural Engineer | J2: Southeast | K2: USA | L2: Electronic Equipment | M2: Active | N2: =H2*12 -> 809640 | O2: =H2*10% -> 6747
A3: 2 | B3: Armstrong | C3: sarmstrong1@infoseek.co.jp | D3: M | E3: Sports | F3: 39538 | G3: 13 | H3: 71869 | I3: Financial Advisor | J3: Southeast | K3: USA | L3: Games & Sports | M3: On Leave | N3: =H3*12 -> 862428 | O3: =H3*10% -> 7186.9
A4: 3 | B4: Carr | C4: fcarr2@woothemes.com | D4: M | E4: Automotive | F4: 40006 | G4: 12 | H4: 101768 | I4: Recruiting Manager | J4: Northwest | K4: USA | L4: Auto & Hardware | M4: Resigned | N4: =H4*12 -> 1221216 | O4: =H4*10% -> 10176.8
A5: 4 | B5: Murray | C5: jmurray3@gov.uk | D5: F | E5: Jewelery | F5: 46746 | G5: 7 | H5: 96897 | I5: Desktop Support Technician | J5: Northwest | K5: USA | L5: Fashion | M5: On Leave | N5: =H5*12 -> 1162764 | O5: =H5*10% -> 9689.7
A6: 5 | B6: Ellis | C6: jellis4@sciencedirect.com | D6: F | E6: Grocery | F6: 37518 | G6: 19 | H6: 63702 | I6: Software Engineer III | J6: Nova Scotia | K6: Canada | L6: Domestic | M6: Active | N6: =H6*12 -> 764424 | O6: =H6*10% -> 6370.2
A7: 6 | B7: Phillips | C7: bphillips5@time.com | D7: M | E7: Tools | F7: 41507 | G7: 8 | H7: 118497 | I7: Executive Secretary | J7: Northeast | K7: USA | L7: Auto & Hardware | M7: Active | N7: =H7*12 -> 1421964 | O7: =H7*10% -> 11849.7
A8: 7 | B8: Williamson | C8: rwilliamson6@ted.com | D8: M | E8: Computers | F8: 38851 | G8: 15 | H8: 65889 | I8: Dental Hygienist | J8: Quebec | K8: Canada | L8: Electronic Equipment | M8: Active | N8: =H8*12 -> 790668 | O8: =H8*10% -> 6588.9
A9: 8 | B9: Harris | C9: aharris7@ucoz.com | D9: F | E9: Toys | F9: 37845 | G9: 18 | H9: 84427 | I9: Safety Technician I | J9: Southwest | K9: USA | L9: Games & Sports | M9: Active | N9: =H9*12 -> 1013124 | O9: =H9*10% -> 8442.7
A10: 9 | B10: James | C10: rjames8@prnewswire.com | D10: M | E10: Jewelery | F10: 38602 | G10: 16 | H10: 108657 | I10: Sales Associate | J10: Southeast | K10: USA | L10: Fashion | M10: Active | N10: =H10*12 -> 1303884 | O10: =H10*10% -> 10865.7
A11: 10 | B11: Sanchez | C11: rsanchez9@cloudflare.com | D11: M | E11: Movies | F11: 41346 | G11: 8 | H11: 108093 | I11: Sales Representative | J11: Northeast | K11: USA | L11: Entertainment | M11: On Leave | N11: =H11*12 -> 1297116 | O11: =H11*10% -> 10809.3
A12: 11 | B12: Jacobs | C12: jjacobsa@sbwire.com | D12: F | E12: Jewelery | F12: 37952 | G12: 18 | H12: 121966 | I12: Community Outreach Specialist | J12: Nova Scotia | K12: Canada | L12: Fashion | M12: On Leave | N12: =H12*12 -> 1463592 | O12: =H12*10% -> 12196.6
A13: 12 | B13: Black | C13: mblackb@edublogs.org | D13: M | E13: Clothing | F13: 37656 | G13: 18 | H13: 44179 | I13: Data Coordiator | J13: Nova Scotia | K13: Canada | L13: Domestic | M13: Resigned | N13: =H13*12 -> 530148 | O13: =H13*10% -> 4417.9
... A1001: 1000 | B1001: Howard | C1001: showardrr@addtoany.com | D1001: M | E1001: Baby | F1001: 37932 | G1001: 18 | H1001: 148687 | I1001: General Manager | J1001: Northwest | K1001: USA | L1001: Domestic | M1001: Active | N1001: =H1001*12 -> 1784244 | O1001: =H1001*10% -> 14868.7
A1002: Total | D1002: =SUBTOTAL(103,datatable[Sex]) -> 1000 | L1002: =SUBTOTAL(103,datatable[Divisons]) -> 1000 | O1002: =SUBTOTAL(109,datatable[BONUS]) -> 9733122.3

Sheet Analysis(4)
C1: Total No. of Employees? | D1: =B1014 -> 1000
C2: Which dept. has most employees? | D2: {=_xlfn.LET( _xlpm.Department,_xlfn.UNIQUE(E14:E1013), _xlpm.counts,COUNTIF(E14:E1013,_xlpm.Department), INDEX(_xlpm.Department,MATCH(MAX(_xlpm.counts),_xlpm.counts,0)) )} -> Clothing
C3: Which dept. has highest avg salary? | D3: {=_xlfn.LET(_xlpm.department,_xlfn.UNIQUE(E14:E1013),_xlpm.Averages,AVERAGEIF(E14:E1013,_xlpm.department,H14:H1013),_xlfn._xlws.FILTER(_xlfn.HSTACK(_xlpm.department,_xlpm.Averages),_xlpm.Averages=MAX(_xlpm.Averages)))} -> Outdoors | E3: 112055.42
C4: Which region has the most employees? | D4: {=_xlfn.LET( _xlpm.Region,_xlfn.UNIQUE(J14:J1013), _xlpm.counts,COUNTIF(J14:J1013,_xlpm.Region), INDEX(_xlpm.Region,MATCH(MAX(_xlpm.counts),_xlpm.counts,0)) )} -> Southwest
C5: How many emp are active,resign and on leave? | D5: {=_xlfn.LET(_xlpm.status,_xlfn.UNIQUE(M14:M1013),_xlpm.counts,COUNTIF(M14:M1013,_xlpm.status),_xlfn.HSTACK(_xlpm.status,_xlpm.counts))} -> Active | E5: 853
D6: On Leave | E6: 105
D7: Resigned | E7: 42
C8: what is the average experience? | D8: =AVERAGE(Analysistable[Experience]) -> 13.888
C9: which job titles have the highest salary? | D9: =_xlfn.LET( _xlpm.Jobtitle,_xlfn.UNIQUE(I14:I1013),_xlpm.maximum,MAX(H14:H1013),INDEX(I14:I1013,MATCH(_xlpm.maximum,H14:H1013,0)) ) -> Director of Sales
A13: ID | B13: Last Name | C13: email | D13: Sex | E13: Department | F13: Start date | G13: Experience | H13: Salary | I13: Job title | J13: Region | K13: Country | L13: Divisons | M13: status | N13: Annual Salary | O13: BONUS
A14: ='Data cleaning and validation(3)'!A2 -> 1 | B14: ='Data cleaning and validation(3)'!B2 -> Kelley | C14: ='Data cleaning and validation(3)'!C2 -> rkelley0@soundcloud.com | D14: ='Data cleaning and validation(3)'!D2 -> F | E14: ='Data cleaning and validation(3)'!E2 -> Computers | F14: ='Data cleaning and validation(3)'!F2 -> 44836 | G14: ='Data cleaning and validation(3)'!G2 -> 12 | H14: ='Data cleaning and validation(3)'!H2 -> 67470 | ... O14: ='Data cleaning and validation(3)'!O2 -> 6747
A15: ='Data cleaning and validation(3)'!A3 -> 2 | B15: ='Data cleaning and validation(3)'!B3 -> Armstrong | C15: ='Data cleaning and validation(3)'!C3 -> sarmstrong1@infoseek.co.jp | D15: ='Data cleaning and validation(3)'!D3 -> M | E15: ='Data cleaning and validation(3)'!E3 -> Sports | F15: ='Data cleaning and validation(3)'!F3 -> 39538 | G15: ='Data cleaning and validation(3)'!G3 -> 13 | H15: ='Data cleaning and validation(3)'!H3 -> 71869 | ... O15: ='Data cleaning and validation(3)'!O3 -> 7186.9
A16: ='Data cleaning and validation(3)'!A4 -> 3 | B16: ='Data cleaning and validation(3)'!B4 -> Carr | C16: ='Data cleaning and validation(3)'!C4 -> fcarr2@woothemes.com | D16: ='Data cleaning and validation(3)'!D4 -> M | E16: ='Data cleaning and validation(3)'!E4 -> Automotive | F16: ='Data cleaning and validation(3)'!F4 -> 40006 | G16: ='Data cleaning and validation(3)'!G4 -> 12 | H16: ='Data cleaning and validation(3)'!H4 -> 101768 | ... O16: ='Data cleaning and validation(3)'!O4 -> 10176.8
A17: ='Data cleaning and validation(3)'!A5 -> 4 | B17: ='Data cleaning and validation(3)'!B5 -> Murray | C17: ='Data cleaning and validation(3)'!C5 -> jmurray3@gov.uk | D17: ='Data cleaning and validation(3)'!D5 -> F | E17: ='Data cleaning and validation(3)'!E5 -> Jewelery | F17: ='Data cleaning and validation(3)'!F5 -> 46746 | G17: ='Data cleaning and validation(3)'!G5 -> 7 | H17: ='Data cleaning and validation(3)'!H5 -> 96897 | ... O17: ='Data cleaning and validation(3)'!O5 -> 9689.7
A18: ='Data cleaning and validation(3)'!A6 -> 5 | B18: ='Data cleaning and validation(3)'!B6 -> Ellis | C18: ='Data cleaning and validation(3)'!C6 -> jellis4@sciencedirect.com | D18: ='Data cleaning and validation(3)'!D6 -> F | E18: ='Data cleaning and validation(3)'!E6 -> Grocery | F18: ='Data cleaning and validation(3)'!F6 -> 37518 | G18: ='Data cleaning and validation(3)'!G6 -> 19 | H18: ='Data cleaning and validation(3)'!H6 -> 63702 | ... O18: ='Data cleaning and validation(3)'!O6 -> 6370.2
A19: ='Data cleaning and validation(3)'!A7 -> 6 | B19: ='Data cleaning and validation(3)'!B7 -> Phillips | C19: ='Data cleaning and validation(3)'!C7 -> bphillips5@time.com | D19: ='Data cleaning and validation(3)'!D7 -> M | E19: ='Data cleaning and validation(3)'!E7 -> Tools | F19: ='Data cleaning and validation(3)'!F7 -> 41507 | G19: ='Data cleaning and validation(3)'!G7 -> 8 | H19: ='Data cleaning and validation(3)'!H7 -> 118497 | ... O19: ='Data cleaning and validation(3)'!O7 -> 11849.7
A20: ='Data cleaning and validation(3)'!A8 -> 7 | B20: ='Data cleaning and validation(3)'!B8 -> Williamson | C20: ='Data cleaning and validation(3)'!C8 -> rwilliamson6@ted.com | D20: ='Data cleaning and validation(3)'!D8 -> M | E20: ='Data cleaning and validation(3)'!E8 -> Computers | F20: ='Data cleaning and validation(3)'!F8 -> 38851 | G20: ='Data cleaning and validation(3)'!G8 -> 15 | H20: ='Data cleaning and validation(3)'!H8 -> 65889 | ... O20: ='Data cleaning and validation(3)'!O8 -> 6588.9
A21: ='Data cleaning and validation(3)'!A9 -> 8 | B21: ='Data cleaning and validation(3)'!B9 -> Harris | C21: ='Data cleaning and validation(3)'!C9 -> aharris7@ucoz.com | D21: ='Data cleaning and validation(3)'!D9 -> F | E21: ='Data cleaning and validation(3)'!E9 -> Toys | F21: ='Data cleaning and validation(3)'!F9 -> 37845 | G21: ='Data cleaning and validation(3)'!G9 -> 18 | H21: ='Data cleaning and validation(3)'!H9 -> 84427 | ... O21: ='Data cleaning and validation(3)'!O9 -> 8442.7
A22: ='Data cleaning and validation(3)'!A10 -> 9 | B22: ='Data cleaning and validation(3)'!B10 -> James | C22: ='Data cleaning and validation(3)'!C10 -> rjames8@prnewswire.com | D22: ='Data cleaning and validation(3)'!D10 -> M | E22: ='Data cleaning and validation(3)'!E10 -> Jewelery | F22: ='Data cleaning and validation(3)'!F10 -> 38602 | G22: ='Data cleaning and validation(3)'!G10 -> 16 | H22: ='Data cleaning and validation(3)'!H10 -> 108657 | ... O22: ='Data cleaning and validation(3)'!O10 -> 10865.7
A23: ='Data cleaning and validation(3)'!A11 -> 10 | B23: ='Data cleaning and validation(3)'!B11 -> Sanchez | C23: ='Data cleaning and validation(3)'!C11 -> rsanchez9@cloudflare.com | D23: ='Data cleaning and validation(3)'!D11 -> M | E23: ='Data cleaning and validation(3)'!E11 -> Movies | F23: ='Data cleaning and validation(3)'!F11 -> 41346 | G23: ='Data cleaning and validation(3)'!G11 -> 8 | H23: ='Data cleaning and validation(3)'!H11 -> 108093 | ... O23: ='Data cleaning and validation(3)'!O11 -> 10809.3
A24: ='Data cleaning and validation(3)'!A12 -> 11 | B24: ='Data cleaning and validation(3)'!B12 -> Jacobs | C24: ='Data cleaning and validation(3)'!C12 -> jjacobsa@sbwire.com | D24: ='Data cleaning and validation(3)'!D12 -> F | E24: ='Data cleaning and validation(3)'!E12 -> Jewelery | F24: ='Data cleaning and validation(3)'!F12 -> 37952 | G24: ='Data cleaning and validation(3)'!G12 -> 18 | H24: ='Data cleaning and validation(3)'!H12 -> 121966 | ... O24: ='Data cleaning and validation(3)'!O12 -> 12196.6
A25: ='Data cleaning and validation(3)'!A13 -> 12 | B25: ='Data cleaning and validation(3)'!B13 -> Black | C25: ='Data cleaning and validation(3)'!C13 -> mblackb@edublogs.org | D25: ='Data cleaning and validation(3)'!D13 -> M | E25: ='Data cleaning and validation(3)'!E13 -> Clothing | F25: ='Data cleaning and validation(3)'!F13 -> 37656 | G25: ='Data cleaning and validation(3)'!G13 -> 18 | H25: ='Data cleaning and validation(3)'!H13 -> 44179 | ... O25: ='Data cleaning and validation(3)'!O13 -> 4417.9
... A1013: ='Data cleaning and validation(3)'!A1001 -> 1000 | B1013: ='Data cleaning and validation(3)'!B1001 -> Howard | C1013: ='Data cleaning and validation(3)'!C1001 -> showardrr@addtoany.com | D1013: ='Data cleaning and validation(3)'!D1001 -> M | E1013: ='Data cleaning and validation(3)'!E1001 -> Baby | F1013: ='Data cleaning and validation(3)'!F1001 -> 37932 | G1013: ='Data cleaning and validation(3)'!G1001 -> 18 | H1013: ='Data cleaning and validation(3)'!H1001 -> 148687 | ... O1013: ='Data cleaning and validation(3)'!O1001 -> 14868.7
A1014: Total | B1014: =SUBTOTAL(103,Analysistable[Last Name]) -> 1000 | O1014: =SUBTOTAL(109,Analysistable[BONUS]) -> 9733122.3

Sheet Pivot Tables(5) 
A3: Row Labels | B3: Average of Salary | C3: Count of ID | E3: Count of ID | F3: Column Labels
A4: Automotive | B4: 99658 | C4: 46 | E4: Row Labels | F4: Active | G4: On Leave | H4: Resigned | I4: Grand Total
A5: Baby | B5: 93749.422 | C5: 45 | E5: Northeast | F5: 121 | G5: 18 | H5: 5 | I5: 144
A6: Beauty | B6: 103416.28 | C6: 53 | E6: Northwest | F6: 107 | G6: 14 | H6: 8 | I6: 129
A7: Books | B7: 94890.149 | C7: 47 | E7: Nova Scotia | F7: 136 | G7: 17 | H7: 6 | I7: 159
A8: Clothing | B8: 95054.528 | C8: 53 | E8: Quebec | F8: 105 | G8: 9 | H8: 3 | I8: 117
A9: Computers | B9: 99095.442 | C9: 52 | E9: Southeast | F9: 130 | G9: 16 | H9: 8 | I9: 154
A10: Electronics | B10: 91615.122 | C10: 49 | E10: Grand Total | F10: 599 | G10: 74 | H10: 30 | I10: 703
A11: Games | B11: 103883.76 | C11: 49
A12: Garden | B12: 101959.26 | C12: 47
A13: Grocery | B13: 101113.93 | C13: 46
A14: Health | B14: 98975.652 | C14: 46
A15: Home | B15: 92734.712 | C15: 52 | E15: Row Labels | F15: Count of ID
A16: Industrial | B16: 92900.851 | C16: 47 | E16: 7 | F16: 44
A17: Jewelery | B17: 87812.217 | C17: 46 | E17: 8 | F17: 60
A18: Kids | B18: 93237.553 | C18: 38 | E18: 9 | F18: 48
A19: Movies | B19: 100911.81 | C19: 36 | E19: 10 | F19: 45
A20: Music | B20: 88507.216 | C20: 37 | E20: 11 | F20: 45
A21: Outdoors | B21: 112055.42 | C21: 48 | E21: 12 | F21: 51
A22: Shoes | B22: 92281.814 | C22: 43 | E22: 13 | F22: 51
A23: Sports | B23: 93901.025 | C23: 40 | E23: 14 | F23: 49
A24: Tools | B24: 105020.72 | C24: 39 | E24: 15 | F24: 48
A25: Toys | B25: 96187.171 | C25: 41 | E25: 16 | F25: 52
E26: 17 | F26: 42
E27: 18 | F27: 40
E28: 19 | F28: 48
E29: 20 | F29: 43
E30: 21 | F30: 37
E31: Grand Total | F31: 703

Sheet Insights
A1: EMPLOYEE DATA ANALYSIS — KEY INSIGHTS
A4: No. | B4: Insight | C4: Supporting Metric
A5: 1 | B5: Clothing has the highest number of employees, with 53 employees. | C5: Department employee count
A6: 2 | B6: Outdoors has the highest average salary at ₹112,055. | C6: Department average salary
A7: 3 | B7: Active employees make up 85.2% of the workforce (853 of 1001 employees). | C7: Employment status
A8: 4 | B8: Southwest is the largest region by employee count, with 168 employees. | C8: Regional employee count
A9: 5 | B9: USA has the largest employee population, with 594 employees. | C9: Country employee count
A10: 6 | B10: The highest individual salary is ₹149,929 for the role of Director of Sales. | C10: Maximum salary

Sheet Reference sheet 
A1: REFERENCE SHEET FOR DATA VALIDATION
A13: status | C13: Region | E13: Country
A14: On Leave | C14: Northeast | E14: USA
A15: Active | C15: Northwest | E15: Canada
A16: Resigned | C16: Southwest
C17: Southeast
C18: Nova Scotia
C19: British Columbia
C20: Quebec
